json_arg/__init__.py
json_arg/argparse_schema/__init__.py
json_arg/argparse_schema/argparse_schema.py
json_arg/argparse_schema/LICENSE
json_arg/argparse_schema/README.md
json_arg/argparse_to_json/__init__.py
json_arg/argparse_to_json/converter.py
json_arg/argparse_to_json/LICENSE
json_arg/argparse_to_json/README.md
json_arg/json_argparse.py
json_arg-0.1.2.dist-info/entry_points.txt
json_arg-0.1.2.dist-info/LICENSE
json_arg-0.1.2.dist-info/METADATA
json_arg-0.1.2.dist-info/WHEEL
json_arg-0.1.2.dist-info/RECORD
