Metadata-Version: 2.1
Name: json-arg
Version: 0.1.2
Summary: Load json as args and save args to json. Convert arg parser to json-schema and convert json-schema to arg parser
Home-page: https://github.com/XiLaiTL/json-arg
License: MIT
Keywords: json,schema,argparse,jsonschema,parser,parse,arg
Author: XiLaiTL
Author-email: xilaitl@qq.com
Requires-Python: >=3.8,<4.0
Classifier: License :: OSI Approved :: MIT License
Classifier: Programming Language :: Python :: 3
Classifier: Programming Language :: Python :: 3.8
Classifier: Programming Language :: Python :: 3.9
Classifier: Programming Language :: Python :: 3.10
Classifier: Programming Language :: Python :: 3.11
Classifier: Programming Language :: Python :: 3.12
Classifier: Programming Language :: Python :: 3.13
Classifier: Topic :: File Formats :: JSON
Classifier: Topic :: File Formats :: JSON :: JSON Schema
Classifier: Topic :: Software Development :: Build Tools
Classifier: Topic :: Software Development :: Libraries :: Python Modules
Classifier: Topic :: Terminals
Project-URL: Repository, https://github.com/XiLaiTL/json-arg
